<?xml version="1.0" encoding="UTF-8" ?>
<!DOCTYPE mapper PUBLIC "-//mybatis.org//DTD Mapper 3.0//EN" "http://mybatis.org/dtd/mybatis-3-mapper.dtd" >
<mapper namespace="com.dlfc.lessee.mapper.HouLeaseInfoMapper" >
  <resultMap id="BaseResultMap" type="com.dlfc.lessee.entity.HouLeaseInfo" >
    <!--
      WARNING - @mbggenerated
      This element is automatically generated by MyBatis Generator, do not modify.
      This element was generated on Wed May 31 17:55:56 CST 2017.
    -->
    <id column="ID" property="id" jdbcType="VARCHAR" />
    <result column="PINDEX" property="pindex" jdbcType="INTEGER" />
    <result column="UID" property="uid" jdbcType="VARCHAR" />
    <result column="EID" property="eid" jdbcType="VARCHAR" />
    <result column="LNO" property="lno" jdbcType="VARCHAR" />
    <result column="SYS_SOURCE" property="sysSource" jdbcType="CHAR" />
    <result column="PREFERENTIAL" property="preferential" jdbcType="CHAR" />
    <result column="ONLINE_PAYMENT" property="onlinePayment" jdbcType="CHAR" />
    <result column="AUDIT_STATUS" property="auditStatus" jdbcType="INTEGER" />
    <result column="LOCK_USERID" property="lockUserid" jdbcType="VARCHAR" />
    <result column="LOCK_TIME" property="lockTime" jdbcType="TIMESTAMP" />
    <result column="RELEASE_TIME" property="releaseTime" jdbcType="TIMESTAMP" />
    <result column="SOURCE_TYPE" property="sourceType" jdbcType="INTEGER" />
    <result column="REJECT_TYPE" property="rejectType" jdbcType="INTEGER" />
    <result column="REJECT_REASON" property="rejectReason" jdbcType="VARCHAR" />
    <result column="RELEASE_STATUS" property="releaseStatus" jdbcType="INTEGER" />
    <result column="SHELF_TYPE" property="shelfType" jdbcType="INTEGER" />
    <result column="SHELF_REASON" property="shelfReason" jdbcType="VARCHAR" />
    <result column="HID" property="hid" jdbcType="VARCHAR" />
    <result column="HOUSE_TYPE" property="houseType" jdbcType="INTEGER" />
    <result column="STATIONID" property="stationid" jdbcType="VARCHAR" />
    <result column="CHECKIN_TIME" property="checkinTime" jdbcType="DATE" />
    <result column="RENT_TYPE" property="rentType" jdbcType="VARCHAR" />
    <result column="LEASE_MODE" property="leaseMode" jdbcType="INTEGER" />
    <result column="RENT" property="rent" jdbcType="DECIMAL" />
    <result column="VILLAGE_NAME" property="villageName" jdbcType="VARCHAR" />
    <result column="DISTRICT" property="district" jdbcType="VARCHAR" />
    <result column="DISTRICT_NAME" property="districtName" jdbcType="VARCHAR" />
    <result column="NO" property="no" jdbcType="VARCHAR" />
    <result column="FLOOR" property="floor" jdbcType="VARCHAR" />
    <result column="BUILD_TIME" property="buildTime" jdbcType="VARCHAR" />
    <result column="APARTMENT_LAYOUT" property="apartmentLayout" jdbcType="VARCHAR" />
    <result column="ORIENTATION" property="orientation" jdbcType="VARCHAR" />
    <result column="DECOR" property="decor" jdbcType="VARCHAR" />
    <result column="DECOR_TIME" property="decorTime" jdbcType="VARCHAR" />
    <result column="FACILITIES" property="facilities" jdbcType="VARCHAR" />
    <result column="ELECTRIC" property="electric" jdbcType="VARCHAR" />
    <result column="FEATURE" property="feature" jdbcType="VARCHAR" />
    <result column="ENVIRONMENT" property="environment" jdbcType="VARCHAR" />
    <result column="REQUIREMENT" property="requirement" jdbcType="VARCHAR" />
    <result column="DESCRIPTION" property="description" jdbcType="VARCHAR" />
    <result column="DCRP_TXT" property="dcrpTxt" jdbcType="VARCHAR" />
    <result column="TITLE" property="title" jdbcType="VARCHAR" />
    <result column="TEL" property="tel" jdbcType="VARCHAR" />
    <result column="CONTACT" property="contact" jdbcType="VARCHAR" />
    <result column="OWNER_COST_ITEMS" property="ownerCostItems" jdbcType="VARCHAR" />
    <result column="OWNER_COST" property="ownerCost" jdbcType="VARCHAR" />
    <result column="FRESH_TIME" property="freshTime" jdbcType="TIMESTAMP" />
    <result column="TO_SPECIAL" property="toSpecial" jdbcType="INTEGER" />
    <result column="LONGITUDE" property="longitude" jdbcType="VARCHAR" />
    <result column="LATITUDE" property="latitude" jdbcType="VARCHAR" />
    <result column="RENTAL_AREA" property="rentalArea" jdbcType="DECIMAL" />
    <result column="ROOM" property="room" jdbcType="VARCHAR" />
    <result column="CREATE_USER" property="createUser" jdbcType="VARCHAR" />
    <result column="CREATE_USER_IDENTITY" property="createUserIdentity" jdbcType="SMALLINT" />
    <result column="CREATE_TIME" property="createTime" jdbcType="TIMESTAMP" />
    <result column="MODIFY_USER_IDENTITY" property="modifyUserIdentity" jdbcType="SMALLINT" />
    <result column="MODIFY_TIME" property="modifyTime" jdbcType="TIMESTAMP" />
    <result column="MODIFY_USER" property="modifyUser" jdbcType="VARCHAR" />
    <result column="DELETE_FLG" property="deleteFlg" jdbcType="SMALLINT" />
    <result column="VERSION" property="version" jdbcType="INTEGER" />
    <result column="STAGES" property="stages" jdbcType="CHAR" />
    <result column="SURROUNDING_FACILITIES" property="surroundingFacilities" jdbcType="VARCHAR" />
  </resultMap>
  <sql id="Example_Where_Clause" >
    <!--
      WARNING - @mbggenerated
      This element is automatically generated by MyBatis Generator, do not modify.
      This element was generated on Wed May 31 17:55:56 CST 2017.
    -->
    <where >
      <foreach collection="oredCriteria" item="criteria" separator="or" >
        <if test="criteria.valid" >
          <trim prefix="(" suffix=")" prefixOverrides="and" >
            <foreach collection="criteria.criteria" item="criterion" >
              <choose >
                <when test="criterion.noValue" >
                  and ${criterion.condition}
                </when>
                <when test="criterion.singleValue" >
                  and ${criterion.condition} #{criterion.value}
                </when>
                <when test="criterion.betweenValue" >
                  and ${criterion.condition} #{criterion.value} and #{criterion.secondValue}
                </when>
                <when test="criterion.listValue" >
                  and ${criterion.condition}
                  <foreach collection="criterion.value" item="listItem" open="(" close=")" separator="," >
                    #{listItem}
                  </foreach>
                </when>
              </choose>
            </foreach>
          </trim>
        </if>
      </foreach>
    </where>
  </sql>
  <sql id="Update_By_Example_Where_Clause" >
    <!--
      WARNING - @mbggenerated
      This element is automatically generated by MyBatis Generator, do not modify.
      This element was generated on Wed May 31 17:55:56 CST 2017.
    -->
    <where >
      <foreach collection="example.oredCriteria" item="criteria" separator="or" >
        <if test="criteria.valid" >
          <trim prefix="(" suffix=")" prefixOverrides="and" >
            <foreach collection="criteria.criteria" item="criterion" >
              <choose >
                <when test="criterion.noValue" >
                  and ${criterion.condition}
                </when>
                <when test="criterion.singleValue" >
                  and ${criterion.condition} #{criterion.value}
                </when>
                <when test="criterion.betweenValue" >
                  and ${criterion.condition} #{criterion.value} and #{criterion.secondValue}
                </when>
                <when test="criterion.listValue" >
                  and ${criterion.condition}
                  <foreach collection="criterion.value" item="listItem" open="(" close=")" separator="," >
                    #{listItem}
                  </foreach>
                </when>
              </choose>
            </foreach>
          </trim>
        </if>
      </foreach>
    </where>
  </sql>
  <sql id="Base_Column_List" >
    <!--
      WARNING - @mbggenerated
      This element is automatically generated by MyBatis Generator, do not modify.
      This element was generated on Wed May 31 17:55:56 CST 2017.
    -->
    ID, PINDEX, UID, EID, LNO, SYS_SOURCE, PREFERENTIAL, ONLINE_PAYMENT, AUDIT_STATUS, 
    LOCK_USERID, LOCK_TIME, RELEASE_TIME, SOURCE_TYPE, REJECT_TYPE, REJECT_REASON, RELEASE_STATUS, 
    SHELF_TYPE, SHELF_REASON, HID, HOUSE_TYPE, STATIONID, CHECKIN_TIME, RENT_TYPE, LEASE_MODE, 
    RENT, VILLAGE_NAME, DISTRICT, DISTRICT_NAME, NO, FLOOR, BUILD_TIME, APARTMENT_LAYOUT, 
    ORIENTATION, DECOR, DECOR_TIME, FACILITIES, ELECTRIC, FEATURE, ENVIRONMENT, REQUIREMENT, 
    DESCRIPTION, DCRP_TXT, TITLE, TEL, CONTACT, OWNER_COST_ITEMS, OWNER_COST, FRESH_TIME, 
    TO_SPECIAL, LONGITUDE, LATITUDE, RENTAL_AREA, ROOM, CREATE_USER, CREATE_USER_IDENTITY, 
    CREATE_TIME, MODIFY_USER_IDENTITY, MODIFY_TIME, MODIFY_USER, DELETE_FLG, VERSION, 
    STAGES, SURROUNDING_FACILITIES
  </sql>
  <select id="selectByExample" resultMap="BaseResultMap" parameterType="com.dlfc.lessee.entity.HouLeaseInfoExample" >
    <!--
      WARNING - @mbggenerated
      This element is automatically generated by MyBatis Generator, do not modify.
      This element was generated on Wed May 31 17:55:56 CST 2017.
    -->
    select
    <if test="distinct" >
      distinct
    </if>
    <include refid="Base_Column_List" />
    from hou_lease_info
    <if test="_parameter != null" >
      <include refid="Example_Where_Clause" />
    </if>
    <if test="orderByClause != null" >
      order by ${orderByClause}
    </if>
  </select>
  <select id="selectByPrimaryKey" resultMap="BaseResultMap" parameterType="java.lang.String" >
    <!--
      WARNING - @mbggenerated
      This element is automatically generated by MyBatis Generator, do not modify.
      This element was generated on Wed May 31 17:55:56 CST 2017.
    -->
    select 
    <include refid="Base_Column_List" />
    from hou_lease_info
    where ID = #{id,jdbcType=VARCHAR}
  </select>
  <delete id="deleteByPrimaryKey" parameterType="java.lang.String" >
    <!--
      WARNING - @mbggenerated
      This element is automatically generated by MyBatis Generator, do not modify.
      This element was generated on Wed May 31 17:55:56 CST 2017.
    -->
    delete from hou_lease_info
    where ID = #{id,jdbcType=VARCHAR}
  </delete>
  <delete id="deleteByExample" parameterType="com.dlfc.lessee.entity.HouLeaseInfoExample" >
    <!--
      WARNING - @mbggenerated
      This element is automatically generated by MyBatis Generator, do not modify.
      This element was generated on Wed May 31 17:55:56 CST 2017.
    -->
    delete from hou_lease_info
    <if test="_parameter != null" >
      <include refid="Example_Where_Clause" />
    </if>
  </delete>
  <insert id="insert" parameterType="com.dlfc.lessee.entity.HouLeaseInfo" >
    <!--
      WARNING - @mbggenerated
      This element is automatically generated by MyBatis Generator, do not modify.
      This element was generated on Wed May 31 17:55:56 CST 2017.
    -->
    insert into hou_lease_info (ID, PINDEX, UID, 
      EID, LNO, SYS_SOURCE, PREFERENTIAL, 
      ONLINE_PAYMENT, AUDIT_STATUS, LOCK_USERID, 
      LOCK_TIME, RELEASE_TIME, SOURCE_TYPE, 
      REJECT_TYPE, REJECT_REASON, RELEASE_STATUS, 
      SHELF_TYPE, SHELF_REASON, HID, 
      HOUSE_TYPE, STATIONID, CHECKIN_TIME, 
      RENT_TYPE, LEASE_MODE, RENT, 
      VILLAGE_NAME, DISTRICT, DISTRICT_NAME, 
      NO, FLOOR, BUILD_TIME, 
      APARTMENT_LAYOUT, ORIENTATION, DECOR, 
      DECOR_TIME, FACILITIES, ELECTRIC, 
      FEATURE, ENVIRONMENT, REQUIREMENT, 
      DESCRIPTION, DCRP_TXT, TITLE, 
      TEL, CONTACT, OWNER_COST_ITEMS, 
      OWNER_COST, FRESH_TIME, TO_SPECIAL, 
      LONGITUDE, LATITUDE, RENTAL_AREA, 
      ROOM, CREATE_USER, CREATE_USER_IDENTITY, 
      CREATE_TIME, MODIFY_USER_IDENTITY, MODIFY_TIME, 
      MODIFY_USER, DELETE_FLG, VERSION, 
      STAGES, SURROUNDING_FACILITIES)
    values (#{id,jdbcType=VARCHAR}, #{pindex,jdbcType=INTEGER}, #{uid,jdbcType=VARCHAR}, 
      #{eid,jdbcType=VARCHAR}, #{lno,jdbcType=VARCHAR}, #{sysSource,jdbcType=CHAR}, #{preferential,jdbcType=CHAR}, 
      #{onlinePayment,jdbcType=CHAR}, #{auditStatus,jdbcType=INTEGER}, #{lockUserid,jdbcType=VARCHAR}, 
      #{lockTime,jdbcType=TIMESTAMP}, #{releaseTime,jdbcType=TIMESTAMP}, #{sourceType,jdbcType=INTEGER}, 
      #{rejectType,jdbcType=INTEGER}, #{rejectReason,jdbcType=VARCHAR}, #{releaseStatus,jdbcType=INTEGER}, 
      #{shelfType,jdbcType=INTEGER}, #{shelfReason,jdbcType=VARCHAR}, #{hid,jdbcType=VARCHAR}, 
      #{houseType,jdbcType=INTEGER}, #{stationid,jdbcType=VARCHAR}, #{checkinTime,jdbcType=DATE}, 
      #{rentType,jdbcType=VARCHAR}, #{leaseMode,jdbcType=INTEGER}, #{rent,jdbcType=DECIMAL}, 
      #{villageName,jdbcType=VARCHAR}, #{district,jdbcType=VARCHAR}, #{districtName,jdbcType=VARCHAR}, 
      #{no,jdbcType=VARCHAR}, #{floor,jdbcType=VARCHAR}, #{buildTime,jdbcType=VARCHAR}, 
      #{apartmentLayout,jdbcType=VARCHAR}, #{orientation,jdbcType=VARCHAR}, #{decor,jdbcType=VARCHAR}, 
      #{decorTime,jdbcType=VARCHAR}, #{facilities,jdbcType=VARCHAR}, #{electric,jdbcType=VARCHAR}, 
      #{feature,jdbcType=VARCHAR}, #{environment,jdbcType=VARCHAR}, #{requirement,jdbcType=VARCHAR}, 
      #{description,jdbcType=VARCHAR}, #{dcrpTxt,jdbcType=VARCHAR}, #{title,jdbcType=VARCHAR}, 
      #{tel,jdbcType=VARCHAR}, #{contact,jdbcType=VARCHAR}, #{ownerCostItems,jdbcType=VARCHAR}, 
      #{ownerCost,jdbcType=VARCHAR}, #{freshTime,jdbcType=TIMESTAMP}, #{toSpecial,jdbcType=INTEGER}, 
      #{longitude,jdbcType=VARCHAR}, #{latitude,jdbcType=VARCHAR}, #{rentalArea,jdbcType=DECIMAL}, 
      #{room,jdbcType=VARCHAR}, #{createUser,jdbcType=VARCHAR}, #{createUserIdentity,jdbcType=SMALLINT}, 
      #{createTime,jdbcType=TIMESTAMP}, #{modifyUserIdentity,jdbcType=SMALLINT}, #{modifyTime,jdbcType=TIMESTAMP}, 
      #{modifyUser,jdbcType=VARCHAR}, #{deleteFlg,jdbcType=SMALLINT}, #{version,jdbcType=INTEGER}, 
      #{stages,jdbcType=CHAR}, #{surroundingFacilities,jdbcType=VARCHAR})
  </insert>
  <insert id="insertSelective" parameterType="com.dlfc.lessee.entity.HouLeaseInfo" >
    <!--
      WARNING - @mbggenerated
      This element is automatically generated by MyBatis Generator, do not modify.
      This element was generated on Wed May 31 17:55:56 CST 2017.
    -->
    insert into hou_lease_info
    <trim prefix="(" suffix=")" suffixOverrides="," >
      <if test="id != null" >
        ID,
      </if>
      <if test="pindex != null" >
        PINDEX,
      </if>
      <if test="uid != null" >
        UID,
      </if>
      <if test="eid != null" >
        EID,
      </if>
      <if test="lno != null" >
        LNO,
      </if>
      <if test="sysSource != null" >
        SYS_SOURCE,
      </if>
      <if test="preferential != null" >
        PREFERENTIAL,
      </if>
      <if test="onlinePayment != null" >
        ONLINE_PAYMENT,
      </if>
      <if test="auditStatus != null" >
        AUDIT_STATUS,
      </if>
      <if test="lockUserid != null" >
        LOCK_USERID,
      </if>
      <if test="lockTime != null" >
        LOCK_TIME,
      </if>
      <if test="releaseTime != null" >
        RELEASE_TIME,
      </if>
      <if test="sourceType != null" >
        SOURCE_TYPE,
      </if>
      <if test="rejectType != null" >
        REJECT_TYPE,
      </if>
      <if test="rejectReason != null" >
        REJECT_REASON,
      </if>
      <if test="releaseStatus != null" >
        RELEASE_STATUS,
      </if>
      <if test="shelfType != null" >
        SHELF_TYPE,
      </if>
      <if test="shelfReason != null" >
        SHELF_REASON,
      </if>
      <if test="hid != null" >
        HID,
      </if>
      <if test="houseType != null" >
        HOUSE_TYPE,
      </if>
      <if test="stationid != null" >
        STATIONID,
      </if>
      <if test="checkinTime != null" >
        CHECKIN_TIME,
      </if>
      <if test="rentType != null" >
        RENT_TYPE,
      </if>
      <if test="leaseMode != null" >
        LEASE_MODE,
      </if>
      <if test="rent != null" >
        RENT,
      </if>
      <if test="villageName != null" >
        VILLAGE_NAME,
      </if>
      <if test="district != null" >
        DISTRICT,
      </if>
      <if test="districtName != null" >
        DISTRICT_NAME,
      </if>
      <if test="no != null" >
        NO,
      </if>
      <if test="floor != null" >
        FLOOR,
      </if>
      <if test="buildTime != null" >
        BUILD_TIME,
      </if>
      <if test="apartmentLayout != null" >
        APARTMENT_LAYOUT,
      </if>
      <if test="orientation != null" >
        ORIENTATION,
      </if>
      <if test="decor != null" >
        DECOR,
      </if>
      <if test="decorTime != null" >
        DECOR_TIME,
      </if>
      <if test="facilities != null" >
        FACILITIES,
      </if>
      <if test="electric != null" >
        ELECTRIC,
      </if>
      <if test="feature != null" >
        FEATURE,
      </if>
      <if test="environment != null" >
        ENVIRONMENT,
      </if>
      <if test="requirement != null" >
        REQUIREMENT,
      </if>
      <if test="description != null" >
        DESCRIPTION,
      </if>
      <if test="dcrpTxt != null" >
        DCRP_TXT,
      </if>
      <if test="title != null" >
        TITLE,
      </if>
      <if test="tel != null" >
        TEL,
      </if>
      <if test="contact != null" >
        CONTACT,
      </if>
      <if test="ownerCostItems != null" >
        OWNER_COST_ITEMS,
      </if>
      <if test="ownerCost != null" >
        OWNER_COST,
      </if>
      <if test="freshTime != null" >
        FRESH_TIME,
      </if>
      <if test="toSpecial != null" >
        TO_SPECIAL,
      </if>
      <if test="longitude != null" >
        LONGITUDE,
      </if>
      <if test="latitude != null" >
        LATITUDE,
      </if>
      <if test="rentalArea != null" >
        RENTAL_AREA,
      </if>
      <if test="room != null" >
        ROOM,
      </if>
      <if test="createUser != null" >
        CREATE_USER,
      </if>
      <if test="createUserIdentity != null" >
        CREATE_USER_IDENTITY,
      </if>
      <if test="createTime != null" >
        CREATE_TIME,
      </if>
      <if test="modifyUserIdentity != null" >
        MODIFY_USER_IDENTITY,
      </if>
      <if test="modifyTime != null" >
        MODIFY_TIME,
      </if>
      <if test="modifyUser != null" >
        MODIFY_USER,
      </if>
      <if test="deleteFlg != null" >
        DELETE_FLG,
      </if>
      <if test="version != null" >
        VERSION,
      </if>
      <if test="stages != null" >
        STAGES,
      </if>
      <if test="surroundingFacilities != null" >
        SURROUNDING_FACILITIES,
      </if>
    </trim>
    <trim prefix="values (" suffix=")" suffixOverrides="," >
      <if test="id != null" >
        #{id,jdbcType=VARCHAR},
      </if>
      <if test="pindex != null" >
        #{pindex,jdbcType=INTEGER},
      </if>
      <if test="uid != null" >
        #{uid,jdbcType=VARCHAR},
      </if>
      <if test="eid != null" >
        #{eid,jdbcType=VARCHAR},
      </if>
      <if test="lno != null" >
        #{lno,jdbcType=VARCHAR},
      </if>
      <if test="sysSource != null" >
        #{sysSource,jdbcType=CHAR},
      </if>
      <if test="preferential != null" >
        #{preferential,jdbcType=CHAR},
      </if>
      <if test="onlinePayment != null" >
        #{onlinePayment,jdbcType=CHAR},
      </if>
      <if test="auditStatus != null" >
        #{auditStatus,jdbcType=INTEGER},
      </if>
      <if test="lockUserid != null" >
        #{lockUserid,jdbcType=VARCHAR},
      </if>
      <if test="lockTime != null" >
        #{lockTime,jdbcType=TIMESTAMP},
      </if>
      <if test="releaseTime != null" >
        #{releaseTime,jdbcType=TIMESTAMP},
      </if>
      <if test="sourceType != null" >
        #{sourceType,jdbcType=INTEGER},
      </if>
      <if test="rejectType != null" >
        #{rejectType,jdbcType=INTEGER},
      </if>
      <if test="rejectReason != null" >
        #{rejectReason,jdbcType=VARCHAR},
      </if>
      <if test="releaseStatus != null" >
        #{releaseStatus,jdbcType=INTEGER},
      </if>
      <if test="shelfType != null" >
        #{shelfType,jdbcType=INTEGER},
      </if>
      <if test="shelfReason != null" >
        #{shelfReason,jdbcType=VARCHAR},
      </if>
      <if test="hid != null" >
        #{hid,jdbcType=VARCHAR},
      </if>
      <if test="houseType != null" >
        #{houseType,jdbcType=INTEGER},
      </if>
      <if test="stationid != null" >
        #{stationid,jdbcType=VARCHAR},
      </if>
      <if test="checkinTime != null" >
        #{checkinTime,jdbcType=DATE},
      </if>
      <if test="rentType != null" >
        #{rentType,jdbcType=VARCHAR},
      </if>
      <if test="leaseMode != null" >
        #{leaseMode,jdbcType=INTEGER},
      </if>
      <if test="rent != null" >
        #{rent,jdbcType=DECIMAL},
      </if>
      <if test="villageName != null" >
        #{villageName,jdbcType=VARCHAR},
      </if>
      <if test="district != null" >
        #{district,jdbcType=VARCHAR},
      </if>
      <if test="districtName != null" >
        #{districtName,jdbcType=VARCHAR},
      </if>
      <if test="no != null" >
        #{no,jdbcType=VARCHAR},
      </if>
      <if test="floor != null" >
        #{floor,jdbcType=VARCHAR},
      </if>
      <if test="buildTime != null" >
        #{buildTime,jdbcType=VARCHAR},
      </if>
      <if test="apartmentLayout != null" >
        #{apartmentLayout,jdbcType=VARCHAR},
      </if>
      <if test="orientation != null" >
        #{orientation,jdbcType=VARCHAR},
      </if>
      <if test="decor != null" >
        #{decor,jdbcType=VARCHAR},
      </if>
      <if test="decorTime != null" >
        #{decorTime,jdbcType=VARCHAR},
      </if>
      <if test="facilities != null" >
        #{facilities,jdbcType=VARCHAR},
      </if>
      <if test="electric != null" >
        #{electric,jdbcType=VARCHAR},
      </if>
      <if test="feature != null" >
        #{feature,jdbcType=VARCHAR},
      </if>
      <if test="environment != null" >
        #{environment,jdbcType=VARCHAR},
      </if>
      <if test="requirement != null" >
        #{requirement,jdbcType=VARCHAR},
      </if>
      <if test="description != null" >
        #{description,jdbcType=VARCHAR},
      </if>
      <if test="dcrpTxt != null" >
        #{dcrpTxt,jdbcType=VARCHAR},
      </if>
      <if test="title != null" >
        #{title,jdbcType=VARCHAR},
      </if>
      <if test="tel != null" >
        #{tel,jdbcType=VARCHAR},
      </if>
      <if test="contact != null" >
        #{contact,jdbcType=VARCHAR},
      </if>
      <if test="ownerCostItems != null" >
        #{ownerCostItems,jdbcType=VARCHAR},
      </if>
      <if test="ownerCost != null" >
        #{ownerCost,jdbcType=VARCHAR},
      </if>
      <if test="freshTime != null" >
        #{freshTime,jdbcType=TIMESTAMP},
      </if>
      <if test="toSpecial != null" >
        #{toSpecial,jdbcType=INTEGER},
      </if>
      <if test="longitude != null" >
        #{longitude,jdbcType=VARCHAR},
      </if>
      <if test="latitude != null" >
        #{latitude,jdbcType=VARCHAR},
      </if>
      <if test="rentalArea != null" >
        #{rentalArea,jdbcType=DECIMAL},
      </if>
      <if test="room != null" >
        #{room,jdbcType=VARCHAR},
      </if>
      <if test="createUser != null" >
        #{createUser,jdbcType=VARCHAR},
      </if>
      <if test="createUserIdentity != null" >
        #{createUserIdentity,jdbcType=SMALLINT},
      </if>
      <if test="createTime != null" >
        #{createTime,jdbcType=TIMESTAMP},
      </if>
      <if test="modifyUserIdentity != null" >
        #{modifyUserIdentity,jdbcType=SMALLINT},
      </if>
      <if test="modifyTime != null" >
        #{modifyTime,jdbcType=TIMESTAMP},
      </if>
      <if test="modifyUser != null" >
        #{modifyUser,jdbcType=VARCHAR},
      </if>
      <if test="deleteFlg != null" >
        #{deleteFlg,jdbcType=SMALLINT},
      </if>
      <if test="version != null" >
        #{version,jdbcType=INTEGER},
      </if>
      <if test="stages != null" >
        #{stages,jdbcType=CHAR},
      </if>
      <if test="surroundingFacilities != null" >
        #{surroundingFacilities,jdbcType=VARCHAR},
      </if>
    </trim>
  </insert>
  <select id="countByExample" parameterType="com.dlfc.lessee.entity.HouLeaseInfoExample" resultType="java.lang.Integer" >
    <!--
      WARNING - @mbggenerated
      This element is automatically generated by MyBatis Generator, do not modify.
      This element was generated on Wed May 31 17:55:56 CST 2017.
    -->
    select count(*) from hou_lease_info
    <if test="_parameter != null" >
      <include refid="Example_Where_Clause" />
    </if>
  </select>
  <update id="updateByExampleSelective" parameterType="map" >
    <!--
      WARNING - @mbggenerated
      This element is automatically generated by MyBatis Generator, do not modify.
      This element was generated on Wed May 31 17:55:56 CST 2017.
    -->
    update hou_lease_info
    <set >
      <if test="record.id != null" >
        ID = #{record.id,jdbcType=VARCHAR},
      </if>
      <if test="record.pindex != null" >
        PINDEX = #{record.pindex,jdbcType=INTEGER},
      </if>
      <if test="record.uid != null" >
        UID = #{record.uid,jdbcType=VARCHAR},
      </if>
      <if test="record.eid != null" >
        EID = #{record.eid,jdbcType=VARCHAR},
      </if>
      <if test="record.lno != null" >
        LNO = #{record.lno,jdbcType=VARCHAR},
      </if>
      <if test="record.sysSource != null" >
        SYS_SOURCE = #{record.sysSource,jdbcType=CHAR},
      </if>
      <if test="record.preferential != null" >
        PREFERENTIAL = #{record.preferential,jdbcType=CHAR},
      </if>
      <if test="record.onlinePayment != null" >
        ONLINE_PAYMENT = #{record.onlinePayment,jdbcType=CHAR},
      </if>
      <if test="record.auditStatus != null" >
        AUDIT_STATUS = #{record.auditStatus,jdbcType=INTEGER},
      </if>
      <if test="record.lockUserid != null" >
        LOCK_USERID = #{record.lockUserid,jdbcType=VARCHAR},
      </if>
      <if test="record.lockTime != null" >
        LOCK_TIME = #{record.lockTime,jdbcType=TIMESTAMP},
      </if>
      <if test="record.releaseTime != null" >
        RELEASE_TIME = #{record.releaseTime,jdbcType=TIMESTAMP},
      </if>
      <if test="record.sourceType != null" >
        SOURCE_TYPE = #{record.sourceType,jdbcType=INTEGER},
      </if>
      <if test="record.rejectType != null" >
        REJECT_TYPE = #{record.rejectType,jdbcType=INTEGER},
      </if>
      <if test="record.rejectReason != null" >
        REJECT_REASON = #{record.rejectReason,jdbcType=VARCHAR},
      </if>
      <if test="record.releaseStatus != null" >
        RELEASE_STATUS = #{record.releaseStatus,jdbcType=INTEGER},
      </if>
      <if test="record.shelfType != null" >
        SHELF_TYPE = #{record.shelfType,jdbcType=INTEGER},
      </if>
      <if test="record.shelfReason != null" >
        SHELF_REASON = #{record.shelfReason,jdbcType=VARCHAR},
      </if>
      <if test="record.hid != null" >
        HID = #{record.hid,jdbcType=VARCHAR},
      </if>
      <if test="record.houseType != null" >
        HOUSE_TYPE = #{record.houseType,jdbcType=INTEGER},
      </if>
      <if test="record.stationid != null" >
        STATIONID = #{record.stationid,jdbcType=VARCHAR},
      </if>
      <if test="record.checkinTime != null" >
        CHECKIN_TIME = #{record.checkinTime,jdbcType=DATE},
      </if>
      <if test="record.rentType != null" >
        RENT_TYPE = #{record.rentType,jdbcType=VARCHAR},
      </if>
      <if test="record.leaseMode != null" >
        LEASE_MODE = #{record.leaseMode,jdbcType=INTEGER},
      </if>
      <if test="record.rent != null" >
        RENT = #{record.rent,jdbcType=DECIMAL},
      </if>
      <if test="record.villageName != null" >
        VILLAGE_NAME = #{record.villageName,jdbcType=VARCHAR},
      </if>
      <if test="record.district != null" >
        DISTRICT = #{record.district,jdbcType=VARCHAR},
      </if>
      <if test="record.districtName != null" >
        DISTRICT_NAME = #{record.districtName,jdbcType=VARCHAR},
      </if>
      <if test="record.no != null" >
        NO = #{record.no,jdbcType=VARCHAR},
      </if>
      <if test="record.floor != null" >
        FLOOR = #{record.floor,jdbcType=VARCHAR},
      </if>
      <if test="record.buildTime != null" >
        BUILD_TIME = #{record.buildTime,jdbcType=VARCHAR},
      </if>
      <if test="record.apartmentLayout != null" >
        APARTMENT_LAYOUT = #{record.apartmentLayout,jdbcType=VARCHAR},
      </if>
      <if test="record.orientation != null" >
        ORIENTATION = #{record.orientation,jdbcType=VARCHAR},
      </if>
      <if test="record.decor != null" >
        DECOR = #{record.decor,jdbcType=VARCHAR},
      </if>
      <if test="record.decorTime != null" >
        DECOR_TIME = #{record.decorTime,jdbcType=VARCHAR},
      </if>
      <if test="record.facilities != null" >
        FACILITIES = #{record.facilities,jdbcType=VARCHAR},
      </if>
      <if test="record.electric != null" >
        ELECTRIC = #{record.electric,jdbcType=VARCHAR},
      </if>
      <if test="record.feature != null" >
        FEATURE = #{record.feature,jdbcType=VARCHAR},
      </if>
      <if test="record.environment != null" >
        ENVIRONMENT = #{record.environment,jdbcType=VARCHAR},
      </if>
      <if test="record.requirement != null" >
        REQUIREMENT = #{record.requirement,jdbcType=VARCHAR},
      </if>
      <if test="record.description != null" >
        DESCRIPTION = #{record.description,jdbcType=VARCHAR},
      </if>
      <if test="record.dcrpTxt != null" >
        DCRP_TXT = #{record.dcrpTxt,jdbcType=VARCHAR},
      </if>
      <if test="record.title != null" >
        TITLE = #{record.title,jdbcType=VARCHAR},
      </if>
      <if test="record.tel != null" >
        TEL = #{record.tel,jdbcType=VARCHAR},
      </if>
      <if test="record.contact != null" >
        CONTACT = #{record.contact,jdbcType=VARCHAR},
      </if>
      <if test="record.ownerCostItems != null" >
        OWNER_COST_ITEMS = #{record.ownerCostItems,jdbcType=VARCHAR},
      </if>
      <if test="record.ownerCost != null" >
        OWNER_COST = #{record.ownerCost,jdbcType=VARCHAR},
      </if>
      <if test="record.freshTime != null" >
        FRESH_TIME = #{record.freshTime,jdbcType=TIMESTAMP},
      </if>
      <if test="record.toSpecial != null" >
        TO_SPECIAL = #{record.toSpecial,jdbcType=INTEGER},
      </if>
      <if test="record.longitude != null" >
        LONGITUDE = #{record.longitude,jdbcType=VARCHAR},
      </if>
      <if test="record.latitude != null" >
        LATITUDE = #{record.latitude,jdbcType=VARCHAR},
      </if>
      <if test="record.rentalArea != null" >
        RENTAL_AREA = #{record.rentalArea,jdbcType=DECIMAL},
      </if>
      <if test="record.room != null" >
        ROOM = #{record.room,jdbcType=VARCHAR},
      </if>
      <if test="record.createUser != null" >
        CREATE_USER = #{record.createUser,jdbcType=VARCHAR},
      </if>
      <if test="record.createUserIdentity != null" >
        CREATE_USER_IDENTITY = #{record.createUserIdentity,jdbcType=SMALLINT},
      </if>
      <if test="record.createTime != null" >
        CREATE_TIME = #{record.createTime,jdbcType=TIMESTAMP},
      </if>
      <if test="record.modifyUserIdentity != null" >
        MODIFY_USER_IDENTITY = #{record.modifyUserIdentity,jdbcType=SMALLINT},
      </if>
      <if test="record.modifyTime != null" >
        MODIFY_TIME = #{record.modifyTime,jdbcType=TIMESTAMP},
      </if>
      <if test="record.modifyUser != null" >
        MODIFY_USER = #{record.modifyUser,jdbcType=VARCHAR},
      </if>
      <if test="record.deleteFlg != null" >
        DELETE_FLG = #{record.deleteFlg,jdbcType=SMALLINT},
      </if>
      <if test="record.version != null" >
        VERSION = #{record.version,jdbcType=INTEGER},
      </if>
      <if test="record.stages != null" >
        STAGES = #{record.stages,jdbcType=CHAR},
      </if>
      <if test="record.surroundingFacilities != null" >
        SURROUNDING_FACILITIES = #{record.surroundingFacilities,jdbcType=VARCHAR},
      </if>
    </set>
    <if test="_parameter != null" >
      <include refid="Update_By_Example_Where_Clause" />
    </if>
  </update>
  <update id="updateByExample" parameterType="map" >
    <!--
      WARNING - @mbggenerated
      This element is automatically generated by MyBatis Generator, do not modify.
      This element was generated on Wed May 31 17:55:56 CST 2017.
    -->
    update hou_lease_info
    set ID = #{record.id,jdbcType=VARCHAR},
      PINDEX = #{record.pindex,jdbcType=INTEGER},
      UID = #{record.uid,jdbcType=VARCHAR},
      EID = #{record.eid,jdbcType=VARCHAR},
      LNO = #{record.lno,jdbcType=VARCHAR},
      SYS_SOURCE = #{record.sysSource,jdbcType=CHAR},
      PREFERENTIAL = #{record.preferential,jdbcType=CHAR},
      ONLINE_PAYMENT = #{record.onlinePayment,jdbcType=CHAR},
      AUDIT_STATUS = #{record.auditStatus,jdbcType=INTEGER},
      LOCK_USERID = #{record.lockUserid,jdbcType=VARCHAR},
      LOCK_TIME = #{record.lockTime,jdbcType=TIMESTAMP},
      RELEASE_TIME = #{record.releaseTime,jdbcType=TIMESTAMP},
      SOURCE_TYPE = #{record.sourceType,jdbcType=INTEGER},
      REJECT_TYPE = #{record.rejectType,jdbcType=INTEGER},
      REJECT_REASON = #{record.rejectReason,jdbcType=VARCHAR},
      RELEASE_STATUS = #{record.releaseStatus,jdbcType=INTEGER},
      SHELF_TYPE = #{record.shelfType,jdbcType=INTEGER},
      SHELF_REASON = #{record.shelfReason,jdbcType=VARCHAR},
      HID = #{record.hid,jdbcType=VARCHAR},
      HOUSE_TYPE = #{record.houseType,jdbcType=INTEGER},
      STATIONID = #{record.stationid,jdbcType=VARCHAR},
      CHECKIN_TIME = #{record.checkinTime,jdbcType=DATE},
      RENT_TYPE = #{record.rentType,jdbcType=VARCHAR},
      LEASE_MODE = #{record.leaseMode,jdbcType=INTEGER},
      RENT = #{record.rent,jdbcType=DECIMAL},
      VILLAGE_NAME = #{record.villageName,jdbcType=VARCHAR},
      DISTRICT = #{record.district,jdbcType=VARCHAR},
      DISTRICT_NAME = #{record.districtName,jdbcType=VARCHAR},
      NO = #{record.no,jdbcType=VARCHAR},
      FLOOR = #{record.floor,jdbcType=VARCHAR},
      BUILD_TIME = #{record.buildTime,jdbcType=VARCHAR},
      APARTMENT_LAYOUT = #{record.apartmentLayout,jdbcType=VARCHAR},
      ORIENTATION = #{record.orientation,jdbcType=VARCHAR},
      DECOR = #{record.decor,jdbcType=VARCHAR},
      DECOR_TIME = #{record.decorTime,jdbcType=VARCHAR},
      FACILITIES = #{record.facilities,jdbcType=VARCHAR},
      ELECTRIC = #{record.electric,jdbcType=VARCHAR},
      FEATURE = #{record.feature,jdbcType=VARCHAR},
      ENVIRONMENT = #{record.environment,jdbcType=VARCHAR},
      REQUIREMENT = #{record.requirement,jdbcType=VARCHAR},
      DESCRIPTION = #{record.description,jdbcType=VARCHAR},
      DCRP_TXT = #{record.dcrpTxt,jdbcType=VARCHAR},
      TITLE = #{record.title,jdbcType=VARCHAR},
      TEL = #{record.tel,jdbcType=VARCHAR},
      CONTACT = #{record.contact,jdbcType=VARCHAR},
      OWNER_COST_ITEMS = #{record.ownerCostItems,jdbcType=VARCHAR},
      OWNER_COST = #{record.ownerCost,jdbcType=VARCHAR},
      FRESH_TIME = #{record.freshTime,jdbcType=TIMESTAMP},
      TO_SPECIAL = #{record.toSpecial,jdbcType=INTEGER},
      LONGITUDE = #{record.longitude,jdbcType=VARCHAR},
      LATITUDE = #{record.latitude,jdbcType=VARCHAR},
      RENTAL_AREA = #{record.rentalArea,jdbcType=DECIMAL},
      ROOM = #{record.room,jdbcType=VARCHAR},
      CREATE_USER = #{record.createUser,jdbcType=VARCHAR},
      CREATE_USER_IDENTITY = #{record.createUserIdentity,jdbcType=SMALLINT},
      CREATE_TIME = #{record.createTime,jdbcType=TIMESTAMP},
      MODIFY_USER_IDENTITY = #{record.modifyUserIdentity,jdbcType=SMALLINT},
      MODIFY_TIME = #{record.modifyTime,jdbcType=TIMESTAMP},
      MODIFY_USER = #{record.modifyUser,jdbcType=VARCHAR},
      DELETE_FLG = #{record.deleteFlg,jdbcType=SMALLINT},
      VERSION = #{record.version,jdbcType=INTEGER},
      STAGES = #{record.stages,jdbcType=CHAR},
      SURROUNDING_FACILITIES = #{record.surroundingFacilities,jdbcType=VARCHAR}
    <if test="_parameter != null" >
      <include refid="Update_By_Example_Where_Clause" />
    </if>
  </update>
  <update id="updateByPrimaryKeySelective" parameterType="com.dlfc.lessee.entity.HouLeaseInfo" >
    <!--
      WARNING - @mbggenerated
      This element is automatically generated by MyBatis Generator, do not modify.
      This element was generated on Wed May 31 17:55:56 CST 2017.
    -->
    update hou_lease_info
    <set >
      <if test="pindex != null" >
        PINDEX = #{pindex,jdbcType=INTEGER},
      </if>
      <if test="uid != null" >
        UID = #{uid,jdbcType=VARCHAR},
      </if>
      <if test="eid != null" >
        EID = #{eid,jdbcType=VARCHAR},
      </if>
      <if test="lno != null" >
        LNO = #{lno,jdbcType=VARCHAR},
      </if>
      <if test="sysSource != null" >
        SYS_SOURCE = #{sysSource,jdbcType=CHAR},
      </if>
      <if test="preferential != null" >
        PREFERENTIAL = #{preferential,jdbcType=CHAR},
      </if>
      <if test="onlinePayment != null" >
        ONLINE_PAYMENT = #{onlinePayment,jdbcType=CHAR},
      </if>
      <if test="auditStatus != null" >
        AUDIT_STATUS = #{auditStatus,jdbcType=INTEGER},
      </if>
      <if test="lockUserid != null" >
        LOCK_USERID = #{lockUserid,jdbcType=VARCHAR},
      </if>
      <if test="lockTime != null" >
        LOCK_TIME = #{lockTime,jdbcType=TIMESTAMP},
      </if>
      <if test="releaseTime != null" >
        RELEASE_TIME = #{releaseTime,jdbcType=TIMESTAMP},
      </if>
      <if test="sourceType != null" >
        SOURCE_TYPE = #{sourceType,jdbcType=INTEGER},
      </if>
      <if test="rejectType != null" >
        REJECT_TYPE = #{rejectType,jdbcType=INTEGER},
      </if>
      <if test="rejectReason != null" >
        REJECT_REASON = #{rejectReason,jdbcType=VARCHAR},
      </if>
      <if test="releaseStatus != null" >
        RELEASE_STATUS = #{releaseStatus,jdbcType=INTEGER},
      </if>
      <if test="shelfType != null" >
        SHELF_TYPE = #{shelfType,jdbcType=INTEGER},
      </if>
      <if test="shelfReason != null" >
        SHELF_REASON = #{shelfReason,jdbcType=VARCHAR},
      </if>
      <if test="hid != null" >
        HID = #{hid,jdbcType=VARCHAR},
      </if>
      <if test="houseType != null" >
        HOUSE_TYPE = #{houseType,jdbcType=INTEGER},
      </if>
      <if test="stationid != null" >
        STATIONID = #{stationid,jdbcType=VARCHAR},
      </if>
      <if test="checkinTime != null" >
        CHECKIN_TIME = #{checkinTime,jdbcType=DATE},
      </if>
      <if test="rentType != null" >
        RENT_TYPE = #{rentType,jdbcType=VARCHAR},
      </if>
      <if test="leaseMode != null" >
        LEASE_MODE = #{leaseMode,jdbcType=INTEGER},
      </if>
      <if test="rent != null" >
        RENT = #{rent,jdbcType=DECIMAL},
      </if>
      <if test="villageName != null" >
        VILLAGE_NAME = #{villageName,jdbcType=VARCHAR},
      </if>
      <if test="district != null" >
        DISTRICT = #{district,jdbcType=VARCHAR},
      </if>
      <if test="districtName != null" >
        DISTRICT_NAME = #{districtName,jdbcType=VARCHAR},
      </if>
      <if test="no != null" >
        NO = #{no,jdbcType=VARCHAR},
      </if>
      <if test="floor != null" >
        FLOOR = #{floor,jdbcType=VARCHAR},
      </if>
      <if test="buildTime != null" >
        BUILD_TIME = #{buildTime,jdbcType=VARCHAR},
      </if>
      <if test="apartmentLayout != null" >
        APARTMENT_LAYOUT = #{apartmentLayout,jdbcType=VARCHAR},
      </if>
      <if test="orientation != null" >
        ORIENTATION = #{orientation,jdbcType=VARCHAR},
      </if>
      <if test="decor != null" >
        DECOR = #{decor,jdbcType=VARCHAR},
      </if>
      <if test="decorTime != null" >
        DECOR_TIME = #{decorTime,jdbcType=VARCHAR},
      </if>
      <if test="facilities != null" >
        FACILITIES = #{facilities,jdbcType=VARCHAR},
      </if>
      <if test="electric != null" >
        ELECTRIC = #{electric,jdbcType=VARCHAR},
      </if>
      <if test="feature != null" >
        FEATURE = #{feature,jdbcType=VARCHAR},
      </if>
      <if test="environment != null" >
        ENVIRONMENT = #{environment,jdbcType=VARCHAR},
      </if>
      <if test="requirement != null" >
        REQUIREMENT = #{requirement,jdbcType=VARCHAR},
      </if>
      <if test="description != null" >
        DESCRIPTION = #{description,jdbcType=VARCHAR},
      </if>
      <if test="dcrpTxt != null" >
        DCRP_TXT = #{dcrpTxt,jdbcType=VARCHAR},
      </if>
      <if test="title != null" >
        TITLE = #{title,jdbcType=VARCHAR},
      </if>
      <if test="tel != null" >
        TEL = #{tel,jdbcType=VARCHAR},
      </if>
      <if test="contact != null" >
        CONTACT = #{contact,jdbcType=VARCHAR},
      </if>
      <if test="ownerCostItems != null" >
        OWNER_COST_ITEMS = #{ownerCostItems,jdbcType=VARCHAR},
      </if>
      <if test="ownerCost != null" >
        OWNER_COST = #{ownerCost,jdbcType=VARCHAR},
      </if>
      <if test="freshTime != null" >
        FRESH_TIME = #{freshTime,jdbcType=TIMESTAMP},
      </if>
      <if test="toSpecial != null" >
        TO_SPECIAL = #{toSpecial,jdbcType=INTEGER},
      </if>
      <if test="longitude != null" >
        LONGITUDE = #{longitude,jdbcType=VARCHAR},
      </if>
      <if test="latitude != null" >
        LATITUDE = #{latitude,jdbcType=VARCHAR},
      </if>
      <if test="rentalArea != null" >
        RENTAL_AREA = #{rentalArea,jdbcType=DECIMAL},
      </if>
      <if test="room != null" >
        ROOM = #{room,jdbcType=VARCHAR},
      </if>
      <if test="createUser != null" >
        CREATE_USER = #{createUser,jdbcType=VARCHAR},
      </if>
      <if test="createUserIdentity != null" >
        CREATE_USER_IDENTITY = #{createUserIdentity,jdbcType=SMALLINT},
      </if>
      <if test="createTime != null" >
        CREATE_TIME = #{createTime,jdbcType=TIMESTAMP},
      </if>
      <if test="modifyUserIdentity != null" >
        MODIFY_USER_IDENTITY = #{modifyUserIdentity,jdbcType=SMALLINT},
      </if>
      <if test="modifyTime != null" >
        MODIFY_TIME = #{modifyTime,jdbcType=TIMESTAMP},
      </if>
      <if test="modifyUser != null" >
        MODIFY_USER = #{modifyUser,jdbcType=VARCHAR},
      </if>
      <if test="deleteFlg != null" >
        DELETE_FLG = #{deleteFlg,jdbcType=SMALLINT},
      </if>
      <if test="version != null" >
        VERSION = #{version,jdbcType=INTEGER},
      </if>
      <if test="stages != null" >
        STAGES = #{stages,jdbcType=CHAR},
      </if>
      <if test="surroundingFacilities != null" >
        SURROUNDING_FACILITIES = #{surroundingFacilities,jdbcType=VARCHAR},
      </if>
    </set>
    where ID = #{id,jdbcType=VARCHAR}
  </update>
  <update id="updateByPrimaryKey" parameterType="com.dlfc.lessee.entity.HouLeaseInfo" >
    <!--
      WARNING - @mbggenerated
      This element is automatically generated by MyBatis Generator, do not modify.
      This element was generated on Wed May 31 17:55:56 CST 2017.
    -->
    update hou_lease_info
    set PINDEX = #{pindex,jdbcType=INTEGER},
      UID = #{uid,jdbcType=VARCHAR},
      EID = #{eid,jdbcType=VARCHAR},
      LNO = #{lno,jdbcType=VARCHAR},
      SYS_SOURCE = #{sysSource,jdbcType=CHAR},
      PREFERENTIAL = #{preferential,jdbcType=CHAR},
      ONLINE_PAYMENT = #{onlinePayment,jdbcType=CHAR},
      AUDIT_STATUS = #{auditStatus,jdbcType=INTEGER},
      LOCK_USERID = #{lockUserid,jdbcType=VARCHAR},
      LOCK_TIME = #{lockTime,jdbcType=TIMESTAMP},
      RELEASE_TIME = #{releaseTime,jdbcType=TIMESTAMP},
      SOURCE_TYPE = #{sourceType,jdbcType=INTEGER},
      REJECT_TYPE = #{rejectType,jdbcType=INTEGER},
      REJECT_REASON = #{rejectReason,jdbcType=VARCHAR},
      RELEASE_STATUS = #{releaseStatus,jdbcType=INTEGER},
      SHELF_TYPE = #{shelfType,jdbcType=INTEGER},
      SHELF_REASON = #{shelfReason,jdbcType=VARCHAR},
      HID = #{hid,jdbcType=VARCHAR},
      HOUSE_TYPE = #{houseType,jdbcType=INTEGER},
      STATIONID = #{stationid,jdbcType=VARCHAR},
      CHECKIN_TIME = #{checkinTime,jdbcType=DATE},
      RENT_TYPE = #{rentType,jdbcType=VARCHAR},
      LEASE_MODE = #{leaseMode,jdbcType=INTEGER},
      RENT = #{rent,jdbcType=DECIMAL},
      VILLAGE_NAME = #{villageName,jdbcType=VARCHAR},
      DISTRICT = #{district,jdbcType=VARCHAR},
      DISTRICT_NAME = #{districtName,jdbcType=VARCHAR},
      NO = #{no,jdbcType=VARCHAR},
      FLOOR = #{floor,jdbcType=VARCHAR},
      BUILD_TIME = #{buildTime,jdbcType=VARCHAR},
      APARTMENT_LAYOUT = #{apartmentLayout,jdbcType=VARCHAR},
      ORIENTATION = #{orientation,jdbcType=VARCHAR},
      DECOR = #{decor,jdbcType=VARCHAR},
      DECOR_TIME = #{decorTime,jdbcType=VARCHAR},
      FACILITIES = #{facilities,jdbcType=VARCHAR},
      ELECTRIC = #{electric,jdbcType=VARCHAR},
      FEATURE = #{feature,jdbcType=VARCHAR},
      ENVIRONMENT = #{environment,jdbcType=VARCHAR},
      REQUIREMENT = #{requirement,jdbcType=VARCHAR},
      DESCRIPTION = #{description,jdbcType=VARCHAR},
      DCRP_TXT = #{dcrpTxt,jdbcType=VARCHAR},
      TITLE = #{title,jdbcType=VARCHAR},
      TEL = #{tel,jdbcType=VARCHAR},
      CONTACT = #{contact,jdbcType=VARCHAR},
      OWNER_COST_ITEMS = #{ownerCostItems,jdbcType=VARCHAR},
      OWNER_COST = #{ownerCost,jdbcType=VARCHAR},
      FRESH_TIME = #{freshTime,jdbcType=TIMESTAMP},
      TO_SPECIAL = #{toSpecial,jdbcType=INTEGER},
      LONGITUDE = #{longitude,jdbcType=VARCHAR},
      LATITUDE = #{latitude,jdbcType=VARCHAR},
      RENTAL_AREA = #{rentalArea,jdbcType=DECIMAL},
      ROOM = #{room,jdbcType=VARCHAR},
      CREATE_USER = #{createUser,jdbcType=VARCHAR},
      CREATE_USER_IDENTITY = #{createUserIdentity,jdbcType=SMALLINT},
      CREATE_TIME = #{createTime,jdbcType=TIMESTAMP},
      MODIFY_USER_IDENTITY = #{modifyUserIdentity,jdbcType=SMALLINT},
      MODIFY_TIME = #{modifyTime,jdbcType=TIMESTAMP},
      MODIFY_USER = #{modifyUser,jdbcType=VARCHAR},
      DELETE_FLG = #{deleteFlg,jdbcType=SMALLINT},
      VERSION = #{version,jdbcType=INTEGER},
      STAGES = #{stages,jdbcType=CHAR},
      SURROUNDING_FACILITIES = #{surroundingFacilities,jdbcType=VARCHAR}
    where ID = #{id,jdbcType=VARCHAR}
  </update>
</mapper>